percy/per.cpython-314-darwin.so
percy_rl-0.1.0.dist-info/licenses/LICENSE
percy_rl-0.1.0.dist-info/METADATA
percy_rl-0.1.0.dist-info/WHEEL
percy_rl-0.1.0.dist-info/top_level.txt
percy_rl-0.1.0.dist-info/RECORD
