Metadata-Version: 2.4
Name: percy-rl
Version: 0.1.0
Summary: Prioritized Experience Replay in C with Python bindings
Author: Redzhep Mehmedov
Author-email: redzhep12@gmail.com
Classifier: Programming Language :: Python
Classifier: Programming Language :: C
Requires-Python: >=3.6
License-File: LICENSE
Dynamic: author
Dynamic: author-email
Dynamic: classifier
Dynamic: description
Dynamic: description-content-type
Dynamic: license-file
Dynamic: requires-python
Dynamic: summary
